{
  "name": "Currency",
  "units": [
    {
      "name": {
        "singular": "Euro",
        "plural": "Euro",
        "abbreviations": [ "EUR" ]
      },
      "func_to_base": "x",
      "func_from_base": "x"
    },
    {
      "name": {
        "singular": "United Arab Emirates dirham",
        "plural": "United Arab Emirates dirhams",
        "abbreviations": [ "AED" ]
      }
    },
    {
      "name": {
        "singular": "Afghan afghani",
        "plural": "Afghan afghani",
        "abbreviations": [ "AFN" ]
      }
    },
    {
      "name": {
        "singular": "Albanian lek",
        "plural": "Albanian lekë",
        "abbreviations": [ "ALL" ]
      }
    },
    {
      "name": {
        "singular": "Armenian dram",
        "plural": "Armenian dram",
        "abbreviations": [ "AMD" ]
      }
    },
    {
      "name": {
        "singular": "Netherlands Antillean guilder",
        "plural": "Netherlands Antillean guilders",
        "abbreviations": [ "ANG" ]
      }
    },
    {
      "name": {
        "singular": "Angolan kwanza",
        "plural": "ngolan kwanzas",
        "abbreviations": [ "AOA" ]
      }
    },
    {
      "name": {
        "singular": "Argentine peso",
        "plural": "Argentine pesos",
        "abbreviations": [ "ARS" ]
      }
    },
    {
      "name": {
        "singular": "Australian dollar",
        "plural": "Australian dollars",
        "abbreviations": [ "AUD" ]
      }
    },
    {
      "name": {
        "singular": "Aruban florin",
        "plural": "Aruban florin",
        "abbreviations": [ "AWG" ]
      }
    },
    {
      "name": {
        "singular": "Azerbaijani manat",
        "plural": "Azerbaijani manat",
        "abbreviations": [ "AZN" ]
      }
    },
    {
      "name": {
        "singular": "Bosnia and Herzegovina convertible mark",
        "plural": "Bosnia and Herzegovina convertible marks",
        "abbreviations": [ "BAM" ]
      }
    },
    {
      "name": {
        "singular": "Barbadian dollar",
        "plural": "Barbadian dollars",
        "abbreviations": [ "BBD" ]
      }
    },
    {
      "name": {
        "singular": "Bangladeshi taka",
        "plural": "Bangladeshi taka",
        "abbreviations": [ "BDT" ]
      }
    },
    {
      "name": {
        "singular": "Bulgarian lev",
        "plural": "Bulgarian leva",
        "abbreviations": [ "BGN" ]
      }
    },
    {
      "name": {
        "singular": "Bahraini dinar",
        "plural": "Bahraini dinar",
        "abbreviations": [ "BHD" ]
      }
    },
    {
      "name": {
        "singular": "Burundian franc",
        "plural": "Burundian franc",
        "abbreviations": [ "BIF" ]
      }
    },
    {
      "name": {
        "singular": "Bermudian dollar",
        "plural": "Bermudian dollars",
        "abbreviations": [ "BMD" ]
      }
    },
    {
      "name": {
        "singular": "Brunei dollar",
        "plural": "Brunei dollars",
        "abbreviations": [ "BND" ]
      }
    },
    {
      "name": {
        "singular": "Bolivian boliviano",
        "plural": "Bolivian boliviano",
        "abbreviations": [ "BOB" ]
      }
    },
    {
      "name": {
        "singular": "Brazilian real",
        "plural": "Brazilian reais",
        "abbreviations": [ "BRL" ]
      }
    },
    {
      "name": {
        "singular": "Bahamian dollar",
        "plural": "Bahamian dollars",
        "abbreviations": [ "BSD" ]
      }
    },
    {
      "name": {
        "singular": "Bitcoin",
        "plural": "Bitcoins",
        "abbreviations": [ "BTC" ]
      }
    },
    {
      "name": {
        "singular": "Bhutanese ngultrum",
        "plural": "Bhutanese ngultrum",
        "abbreviations": [ "BTN" ]
      }
    },
    {
      "name": {
        "singular": "Botswana pula",
        "plural": "Botswana pula",
        "abbreviations": [ "BWP" ]
      }
    },
    {
      "name": {
        "singular": "Belarusian ruble",
        "plural": "Belarusian ruble",
        "abbreviations": [ "BYN" ]
      }
    },
    {
      "name": {
        "singular": "Belize dollar",
        "plural": "Belize dollars",
        "abbreviations": [ "BYN" ]
      }
    },
    {
      "name": {
        "singular": "Canadian dollar",
        "plural": "Canadian dollars",
        "abbreviations": [ "CAD" ]
      }
    },
    {
      "name": {
        "singular": "Chinese yuan",
        "plural": "Chinese yuans",
        "abbreviations": [ "CNY" ]
      }
    },
    {
      "name": {
        "singular": "Croatian kuna",
        "plural": "Croatian kune",
        "abbreviations": [ "HRK" ]
      }
    },
    {
      "name": {
        "singular": "Czech koruna",
        "plural": "Czech korun",
        "abbreviations": [ "CZK" ]
      }
    },
    {
      "name": {
        "singular": "Danish krone",
        "plural": "Danish kroner",
        "abbreviations": [ "DKK" ]
      }
    },
    {
      "name": {
        "singular": "Hong Kong dollar",
        "plural": "Hong Kong dollars",
        "abbreviations": [ "HKD" ]
      }
    },
    {
      "name": {
        "singular": "Hungarian forint",
        "plural": "Hungarian forints",
        "abbreviations": [ "HUF" ]
      }
    },
    {
      "name": {
        "singular": "Icelandic króna",
        "plural": "Icelandic krónur",
        "abbreviations": [ "ISK" ]
      }
    },
    {
      "name": {
        "singular": "Indian rupee",
        "plural": "Indian rupees",
        "abbreviations": [ "INR" ]
      }
    },
    {
      "name": {
        "singular": "Indonesian rupiah",
        "plural": "Indonesian rupiahs",
        "abbreviations": [ "IDR" ]
      }
    },
    {
      "name": {
        "singular": "Israeli shekel",
        "plural": "Israeli shekels",
        "abbreviations": [ "ILS" ]
      }
    },
    {
      "name": {
        "singular": "Japanese yen",
        "plural": "Japanese yens",
        "abbreviations": [ "JPY" ]
      }
    },
    {
      "name": {
        "singular": "New Zealand dollar",
        "plural": "New Zealand dollars",
        "abbreviations": [ "NZD" ]
      }
    },
    {
      "name": {
        "singular": "Norwegian krone",
        "plural": "Norwegian kroner",
        "abbreviations": [ "NOK" ]
      }
    },
    {
      "name": {
        "singular": "Malaysian ringgit",
        "plural": "Malaysian ringgit",
        "abbreviations": [ "MYR" ]
      }
    },
    {
      "name": {
        "singular": "Mexican peso",
        "plural": "Mexican pesos",
        "abbreviations": [ "MXN" ]
      }
    },
    {
      "name": {
        "singular": "Philippine peso",
        "plural": "Philippine pesos",
        "abbreviations": [ "PHP" ]
      }
    },
    {
      "name": {
        "singular": "Polish złoty",
        "plural": "Polish złoty",
        "abbreviations": [ "PLN" ]
      }
    },
    {
      "name": {
        "singular": "Pound sterling",
        "plural": "Pounds sterling",
        "abbreviations": [ "GBP" ]
      }
    },
    {
      "name": {
        "singular": "Romanian leu",
        "plural": "Romanian lei",
        "abbreviations": [ "RON", "LEI" ]
      }
    },
    {
      "name": {
        "singular": "Russian ruble",
        "plural": "Russian rubles",
        "abbreviations": [ "RUB" ]
      }
    },
    {
      "name": {
        "singular": "Singapore dollar",
        "plural": "Singapore dollars",
        "abbreviations": [ "SGD" ]
      }
    },
    {
      "name": {
        "singular": "South African rand",
        "plural": "South African rand",
        "abbreviations": [ "ZAR" ]
      }
    },
    {
      "name": {
        "singular": "South Korean won",
        "plural": "South Korean won",
        "abbreviations": [ "KRW" ]
      }
    },
    {
      "name": {
        "singular": "Swedish krona",
        "plural": "Swedish kronor",
        "abbreviations": [ "SEK" ]
      }
    },
    {
      "name": {
        "singular": "Swiss franc",
        "plural": "Swiss francs",
        "abbreviations": [ "CHF" ]
      }
    },
    {
      "name": {
        "singular": "Thai baht",
        "plural": "Thai baht",
        "abbreviations": [ "THB" ]
      }
    },
    {
      "name": {
        "singular": "Turkish lira",
        "plural": "Turkish liras",
        "abbreviations": [ "TRY" ]
      }
    },
    {
      "name": {
        "singular": "United States dollar",
        "plural": "United States dollars",
        "abbreviations": [ "USD" ]
      }
    }
  ]
}